colab_transfer/__init__.py
colab_transfer/google_drive.py
colab_transfer/transfer.py
colab_transfer/utils.py
colab_transfer/tests/__init__.py
colab_transfer/tests/test_google_drive.py
colab_transfer/tests/test_transfer.py
colab_transfer/tests/test_utils.py
Google_Colab_Transfer-0.1.6.dist-info/LICENSE
Google_Colab_Transfer-0.1.6.dist-info/METADATA
Google_Colab_Transfer-0.1.6.dist-info/WHEEL
Google_Colab_Transfer-0.1.6.dist-info/top_level.txt
Google_Colab_Transfer-0.1.6.dist-info/RECORD
