Metadata-Version: 2.1
Name: Google-Colab-Transfer
Version: 0.1.6
Summary: Transfer data between Colab and Drive.
Home-page: https://github.com/woctezuma/google-colab-transfer
Author: Wok
Author-email: wok@tuta.io
License: UNKNOWN
Download-URL: https://github.com/woctezuma/google-colab-transfer/archive/0.1.6.tar.gz
Keywords: google-colab,google-colaboratory,google-drive
Platform: UNKNOWN
Classifier: Development Status :: 4 - Beta
Classifier: Programming Language :: Python :: 3
Classifier: License :: OSI Approved :: MIT License
Classifier: Operating System :: OS Independent
Requires-Python: >=3
